{
  "workspace": "sdkwork-aiot-backend-sdk",
  "title": "SDKWork AIoT Backend API SDK",
  "apiVersion": "0.1.0",
  "authoritySpec": "../../apis/backend-api/iot/sdkwork-aiot-backend-api.openapi.json",
  "generationInputSpec": "../../apis/backend-api/iot/sdkwork-aiot-backend-api.openapi.json",
  "discoverySurface": {
    "sdkTarget": "backend",
    "apiPrefix": "/backend/v3/api/iot",
    "generatedProtocols": ["http"],
    "manualTransports": []
  },
  "languages": [
    {
      "language": "typescript",
      "workspace": "sdkwork-aiot-backend-sdk-typescript",
      "generationState": "reserved",
      "releaseState": "not_published",
      "name": "@sdkwork/aiot-backend-sdk",
      "version": "0.1.0",
      "description": "SDKWork AIoT backend API generated transport SDK",
      "consumerSurface": {
        "primaryClient": "SdkworkAiotBackendClient",
        "apiPrefix": "/backend/v3/api/iot"
      }
    }
  ]
}
